packit/__init__.py
packit/additional_files.py
packit/core.py
packit/hooks.py
packit/utils.py
packit/commands/__init__.py
packit/commands/packit_test.py
packit/config/__init__.py
packit/config/auto_tests.py
packit/config/base.py
packit/config/dependencies.py
packit/config/description.py
packit/config/extra_files.py
packit/config/extra_meta.py
packit/config/license.py
packit/config/packages.py
packit/config/version/__init__.py
packit/config/version/composite.py
packit/config/version/file.py
packit/config/version/fixed.py
packit/config/version/git_pep440.py
packit/config/version/shell.py
packit-0.30.0.dist-info/LICENSE.txt
packit-0.30.0.dist-info/METADATA
packit-0.30.0.dist-info/WHEEL
packit-0.30.0.dist-info/entry_points.txt
packit-0.30.0.dist-info/top_level.txt
packit-0.30.0.dist-info/RECORD
