Metadata-Version: 2.1
Name: packit
Version: 0.30.0
Summary: Python packaging in declarative way (wrapping pbr to make it flexible)
Home-page: https://pypi.python.org/pypi/packit
Author: NCBI
Author-email: python-core@ncbi.nlm.nih.gov
License: Public Domain
Platform: UNKNOWN
Classifier: License :: Public Domain
Classifier: Environment :: Console
Classifier: Intended Audience :: Developers
Classifier: Intended Audience :: Information Technology
Classifier: Operating System :: OS Independent
Classifier: Programming Language :: Python
Classifier: Programming Language :: Python :: 2
Classifier: Programming Language :: Python :: 2.6
Classifier: Programming Language :: Python :: 2.7
Classifier: Programming Language :: Python :: 3
Classifier: Programming Language :: Python :: 3.3
Classifier: Programming Language :: Python :: 3.4
License-File: LICENSE.txt
Requires-Dist: setuptools (>=8)
Requires-Dist: wheel (>=0.24)
Requires-Dist: pbr (<5.6.0,>=4.0)
Requires-Dist: pip (>=1.5)
Requires-Dist: glob2 (>=0.4.1)
Requires-Dist: packaging (>=16.8)
